ezpyc/__init__.py
ezpyc/clipboard.py
ezpyc/command_decorators.py
ezpyc/env_variable.py
ezpyc/file.py
ezpyc/folder.py
ezpyc/installation_wizard.py
ezpyc/os_decorators.py
ezpyc/output.py
ezpyc-0.1.3.dist-info/licenses/LICENSE
ezpyc-0.1.3.dist-info/METADATA
ezpyc-0.1.3.dist-info/WHEEL
ezpyc-0.1.3.dist-info/top_level.txt
ezpyc-0.1.3.dist-info/RECORD
