Metadata-Version: 2.4
Name: ezpyc
Version: 0.1.3
Summary: Easy Python Commands
Home-page: https://github.com/itonx/ezpyc
Author: Icebreaker
Author-email: ayrton.94.e@gmail.com
Classifier: Programming Language :: Python :: 3
Classifier: License :: OSI Approved :: MIT License
Classifier: Operating System :: OS Independent
Requires-Python: >=3.11
License-File: LICENSE
Dynamic: author
Dynamic: author-email
Dynamic: classifier
Dynamic: description
Dynamic: description-content-type
Dynamic: home-page
Dynamic: license-file
Dynamic: requires-python
Dynamic: summary
